unique_mcp/__init__.py
unique_mcp/auth/zitadel/oauth_proxy.py
unique_mcp/auth/zitadel/oidc_proxy.py
unique_mcp/provider/__init__.py
unique_mcp/provider/base.py
unique_mcp/settings.py
unique_mcp/util/find_env_file.py
unique_mcp-0.1.3.dist-info/WHEEL
unique_mcp-0.1.3.dist-info/entry_points.txt
unique_mcp-0.1.3.dist-info/METADATA
unique_mcp-0.1.3.dist-info/RECORD
