Metadata-Version: 2.3
Name: unique-mcp
Version: 0.1.3
Summary: Add your description here
Author: Cedric Klinkert
Author-email: Cedric Klinkert <cedric@unique.ch>
Requires-Dist: fastmcp>=2.13.3
Requires-Dist: pydantic>=2.12.5
Requires-Dist: pydantic-settings>=2.0.0
Requires-Dist: platformdirs>=4.0.0
Requires-Python: >=3.12
